simpl_temp/__init__.py
simpl_temp/api.py
simpl_temp/cli.py
simpl_temp/core.py
simpl_temp/exceptions.py
simpl_temp/py.typed
simpl_temp-1.0.0.dist-info/licenses/LICENSE
simpl_temp-1.0.0.dist-info/METADATA
simpl_temp-1.0.0.dist-info/WHEEL
simpl_temp-1.0.0.dist-info/entry_points.txt
simpl_temp-1.0.0.dist-info/top_level.txt
simpl_temp-1.0.0.dist-info/RECORD
