Metadata-Version: 2.4
Name: simpl-temp
Version: 1.0.0
Summary: Professional Python library for temporary data management with API support
Author-email: "Kozosvyst Stas (StasX)" <stasx@sxscli.com>
Maintainer-email: "Kozosvyst Stas (StasX)" <stasx@sxscli.com>
License: MIT
Project-URL: Homepage, https://github.com/StasX/simpl-temp
Project-URL: Documentation, https://github.com/StasX/simpl-temp#readme
Project-URL: Repository, https://github.com/StasX/simpl-temp.git
Project-URL: Issues, https://github.com/StasX/simpl-temp/issues
Keywords: temporary,cache,storage,ttl,temp,data,api,fastapi
Classifier: Development Status :: 5 - Production/Stable
Classifier: Intended Audience :: Developers
Classifier: License :: OSI Approved :: MIT License
Classifier: Operating System :: OS Independent
Classifier: Programming Language :: Python :: 3
Classifier: Programming Language :: Python :: 3.8
Classifier: Programming Language :: Python :: 3.9
Classifier: Programming Language :: Python :: 3.10
Classifier: Programming Language :: Python :: 3.11
Classifier: Programming Language :: Python :: 3.12
Classifier: Topic :: Software Development :: Libraries :: Python Modules
Classifier: Topic :: System :: Filesystems
Classifier: Typing :: Typed
Requires-Python: >=3.8
License-File: LICENSE
Provides-Extra: api
Requires-Dist: fastapi>=0.100.0; extra == "api"
Requires-Dist: uvicorn>=0.22.0; extra == "api"
Requires-Dist: pydantic>=2.0.0; extra == "api"
Provides-Extra: dev
Requires-Dist: pytest>=7.0.0; extra == "dev"
Requires-Dist: pytest-cov>=4.0.0; extra == "dev"
Requires-Dist: black>=23.0.0; extra == "dev"
Requires-Dist: isort>=5.12.0; extra == "dev"
Requires-Dist: mypy>=1.0.0; extra == "dev"
Requires-Dist: flake8>=6.0.0; extra == "dev"
Provides-Extra: all
Requires-Dist: simpl-temp[api,dev]; extra == "all"
Dynamic: license-file
